secure_python/__init__.py
secure_python/secure_python.py
secure_python/secure/__init__.py
secure_python/secure/data/__init__.py
secure_python-1.3.4.dist-info/licenses/LICENSE
secure_python-1.3.4.dist-info/METADATA
secure_python-1.3.4.dist-info/WHEEL
secure_python-1.3.4.dist-info/top_level.txt
secure_python-1.3.4.dist-info/RECORD
