Metadata-Version: 2.4
Name: secure_python
Version: 1.3.4
Summary: A framework for encoding and decoding text using custom mappings.
Author: Soundhearddev
License: MIT License
Requires-Python: >=3.7
License-File: LICENSE
Requires-Dist: pycryptodome
Dynamic: license-file
